setup.py
preTeX.egg-info/SOURCES.txt
pretex/Transformer.py
pretex/__init__.py
pretex/pretex.py
pretex/test.py
pretex/trafos.py
pretex.egg-info/PKG-INFO
pretex.egg-info/SOURCES.txt
pretex.egg-info/dependency_links.txt
pretex.egg-info/top_level.txt
pretex/viz/script.js
pretex/viz/style.css