Metadata-Version: 1.0
Name: preTeX
Version: 0.5.1
Summary: LaTeX preprocessor to simplify math typesetting
Home-page: https://github.com/s9w/preTeX
Author: Sebastian Werhausen
Author-email: swerhausen@gmail.com
License: UNKNOWN
Platform: UNKNOWN
